imageidentify/__init__.py
imageidentify/imageidentify.py
imageidentify-0.1.0.dist-info/LICENSE
imageidentify-0.1.0.dist-info/METADATA
imageidentify-0.1.0.dist-info/WHEEL
imageidentify-0.1.0.dist-info/top_level.txt
imageidentify-0.1.0.dist-info/RECORD
