Metadata-Version: 2.1
Name: imageidentify
Version: 0.1.0
Summary: Python package for describing images
Home-page: https://github.com/KalebBerry25/imageidentify
Download-URL: https://github.com/KalebBerry25/imageidentify/archive/0.1.0.tar.gz
Author: D.Quadri and K.Berry
Author-email: kaleb.berry@bison.howard.edu
Classifier: Programming Language :: Python :: 3
Classifier: License :: OSI Approved :: MIT License
Classifier: Operating System :: OS Independent
Requires-Python: >=3
License-File: LICENSE
Requires-Dist: opencv-python
Requires-Dist: numpy
Requires-Dist: tensorflow
